stdlibs/__init__.py
stdlibs/__version__.py
stdlibs/fetch.py
stdlibs/fetch_releases.py
stdlibs/known.py
stdlibs/py.py
stdlibs/py.typed
stdlibs/py2.py
stdlibs/py23.py
stdlibs/py24.py
stdlibs/py25.py
stdlibs/py26.py
stdlibs/py27.py
stdlibs/py3.py
stdlibs/py30.py
stdlibs/py31.py
stdlibs/py310.py
stdlibs/py311.py
stdlibs/py312.py
stdlibs/py313.py
stdlibs/py314.py
stdlibs/py32.py
stdlibs/py33.py
stdlibs/py34.py
stdlibs/py35.py
stdlibs/py36.py
stdlibs/py37.py
stdlibs/py38.py
stdlibs/py39.py
stdlibs/releases.toml
stdlibs/tests/__init__.py
stdlibs/tests/__main__.py
stdlibs-2025.5.10.dist-info/licenses/LICENSE
stdlibs-2025.5.10.dist-info/WHEEL
stdlibs-2025.5.10.dist-info/METADATA
stdlibs-2025.5.10.dist-info/RECORD
