Metadata-Version: 2.4
Name: stdlibs
Version: 2025.5.10
Summary: List of packages in the stdlib
Author-email: Amethyst Reese <amy@n7.gg>
Requires-Python: >=3.8
Classifier: Development Status :: 5 - Production/Stable
Classifier: Intended Audience :: Developers
Classifier: License :: OSI Approved :: MIT License
Classifier: Topic :: Utilities
Classifier: Typing :: Typed
License-File: LICENSE
Requires-Dist: attribution==1.8.0 ; extra == "dev"
Requires-Dist: build>=1 ; extra == "dev"
Requires-Dist: black==25.1.0 ; extra == "dev"
Requires-Dist: coverage==7.8.0 ; extra == "dev"
Requires-Dist: fissix==24.4.24 ; extra == "dev"
Requires-Dist: flake8==7.2.0 ; extra == "dev"
Requires-Dist: flit==3.12.0 ; extra == "dev"
Requires-Dist: mypy==1.15.0 ; extra == "dev"
Requires-Dist: packaging==25.0 ; extra == "dev"
Requires-Dist: ufmt==2.8.0 ; extra == "dev"
Requires-Dist: usort==1.0.8.post1 ; extra == "dev"
Requires-Dist: sphinx==8.1.3 ; extra == "docs"
Requires-Dist: sphinx-mdinclude==0.6.2 ; extra == "docs"
Project-URL: Documentation, https://stdlibs.omnilib.dev/en/latest/
Project-URL: Github, https://github.com/omnilib/stdlibs
Project-URL: Homepage, https://stdlibs.omnilib.dev
Provides-Extra: dev
Provides-Extra: docs
